FileBackup/CommandLine/CommandLineArguments.py
FileBackup/CommandLine/EntryPoint.py
FileBackup/CommandLine/MirrorEntryPoint.py
FileBackup/CommandLine/OffsiteEntryPoint.py
FileBackup/CommandLine/__init__.py
FileBackup/DataStore/FastGlacierDataStore.py
FileBackup/DataStore/FileSystemDataStore.py
FileBackup/DataStore/Interfaces/BulkStorageDataStore.py
FileBackup/DataStore/Interfaces/DataStore.py
FileBackup/DataStore/Interfaces/FileBasedDataStore.py
FileBackup/DataStore/Interfaces/__init__.py
FileBackup/DataStore/S3BrowserDataStore.py
FileBackup/DataStore/SFTPDataStore.py
FileBackup/DataStore/__init__.py
FileBackup/Impl/Common.py
FileBackup/Impl/__init__.py
FileBackup/Mirror.py
FileBackup/Offsite.py
FileBackup/Snapshot.py
FileBackup/__init__.py
FileBackup/py.typed
filebackup-0.5.4.dist-info/WHEEL
filebackup-0.5.4.dist-info/entry_points.txt
filebackup-0.5.4.dist-info/METADATA
filebackup-0.5.4.dist-info/RECORD
