Metadata-Version: 2.4
Name: filebackup
Version: 0.5.4
Summary: Tool for creating and restoring file system backups.
Keywords: backup,mirror,offsite,restore
Author: David Brownell
Author-email: David Brownell <github@DavidBrownell.com>
License-Expression: MIT
Classifier: Development Status :: 4 - Beta
Classifier: Environment :: Console
Classifier: Intended Audience :: Developers
Classifier: Intended Audience :: End Users/Desktop
Classifier: Intended Audience :: System Administrators
Classifier: Natural Language :: English
Classifier: Operating System :: MacOS
Classifier: Operating System :: Microsoft :: Windows
Classifier: Operating System :: POSIX :: Linux
Classifier: Programming Language :: Python
Classifier: Programming Language :: Python :: 3.10
Classifier: Programming Language :: Python :: 3.11
Classifier: Programming Language :: Python :: 3.12
Classifier: Programming Language :: Python :: 3.13
Classifier: Topic :: System :: Archiving :: Backup
Classifier: Topic :: System :: Archiving :: Mirroring
Classifier: Topic :: System :: Systems Administration
Classifier: Topic :: Utilities
Requires-Dist: dbrownell-common>=0.15.0
Requires-Dist: paramiko>=3.5.1
Requires-Dist: typer>=0.15.3
Requires-Python: >=3.10
Project-URL: Documentation, https://github.com/davidbrownell/FileBackup
Project-URL: Homepage, https://github.com/davidbrownell/FileBackup
Project-URL: Repository, https://github.com/davidbrownell/FileBackup
